moy_nalog/__init__.py
moy_nalog/client.py
moy_nalog/enums.py
moy_nalog/exceptions.py
moy_nalog/models.py
moy_nalog_api-1.0.3.dist-info/METADATA
moy_nalog_api-1.0.3.dist-info/WHEEL
moy_nalog_api-1.0.3.dist-info/licenses/LICENSE
moy_nalog_api-1.0.3.dist-info/RECORD
