Metadata-Version: 2.4
Name: moy-nalog-api
Version: 1.0.3
Summary: The most complete async Python client for Russian self-employed tax service (Moy Nalog / lknpd.nalog.ru)
Project-URL: Homepage, https://github.com/inache-su/moy-nalog-api
Project-URL: Documentation, https://github.com/inache-su/moy-nalog-api#readme
Project-URL: Repository, https://github.com/inache-su/moy-nalog-api
Project-URL: Issues, https://github.com/inache-su/moy-nalog-api/issues
Project-URL: Changelog, https://github.com/inache-su/moy-nalog-api/blob/main/CHANGELOG.md
Author-email: Kirill Nikulin <me@kirodev.eu>
License-Expression: MIT
License-File: LICENSE
Keywords: api,async,fns,httpx,moy-nalog,nalog,npd,pydantic,receipt,russia,samozanyatiy,self-employed,tax
Classifier: Development Status :: 5 - Production/Stable
Classifier: Framework :: AsyncIO
Classifier: Framework :: Pydantic :: 2
Classifier: Intended Audience :: Developers
Classifier: License :: OSI Approved :: MIT License
Classifier: Operating System :: OS Independent
Classifier: Programming Language :: Python :: 3
Classifier: Programming Language :: Python :: 3.10
Classifier: Programming Language :: Python :: 3.11
Classifier: Programming Language :: Python :: 3.12
Classifier: Programming Language :: Python :: 3.13
Classifier: Topic :: Office/Business :: Financial :: Accounting
Classifier: Typing :: Typed
Requires-Python: >=3.10
Requires-Dist: httpx>=0.25.0
Requires-Dist: pydantic>=2.0.0
Provides-Extra: dev
Requires-Dist: mypy>=1.0.0; extra == 'dev'
Requires-Dist: pytest-asyncio>=0.21.0; extra == 'dev'
Requires-Dist: pytest-cov>=4.0.0; extra == 'dev'
Requires-Dist: pytest>=7.0.0; extra == 'dev'
Requires-Dist: python-dotenv>=1.0.0; extra == 'dev'
Requires-Dist: ruff>=0.1.0; extra == 'dev'
Provides-Extra: socks
Requires-Dist: httpx-socks>=0.9.0; extra == 'socks'
